muffler-0.2.0.dist-info/METADATA
muffler-0.2.0.dist-info/WHEEL
muffler-0.2.0.dist-info/licenses/LICENSE
muffler/__init__.py
muffler/muffler.pyi
muffler/py.typed
muffler/muffler.pypy310-pp73-x86-linux-gnu.so
muffler-0.2.0.dist-info/RECORD
